pyhanlp/__init__.py
pyhanlp/main.py
pyhanlp/server.py
pyhanlp/util.py
pyhanlp/static/__init__.py
pyhanlp/static/hanlp.properties.in
pyhanlp/static/index.html
yyhanlp-0.1.85.dist-info/LICENSE
yyhanlp-0.1.85.dist-info/METADATA
yyhanlp-0.1.85.dist-info/WHEEL
yyhanlp-0.1.85.dist-info/entry_points.txt
yyhanlp-0.1.85.dist-info/top_level.txt
yyhanlp-0.1.85.dist-info/RECORD
