Metadata-Version: 2.1
Name: yyhanlp
Version: 0.1.85
Summary: Python wrapper for HanLP: Han Language Processing
Home-page: https://github.com/hankcs/pyhanlp
Author: hankcs
Author-email: hankcshe@gmail.com
License: Apache License 2.0
Keywords: corpus,machine-learning,NLU,NLP
Classifier: Intended Audience :: Developers
Classifier: Natural Language :: Chinese (Simplified)
Classifier: Natural Language :: Chinese (Traditional)
Classifier: Operating System :: OS Independent
Classifier: Programming Language :: Python
Classifier: Programming Language :: Python :: 2
Classifier: Programming Language :: Python :: 2.7
Classifier: Programming Language :: Python :: 3
Classifier: Topic :: Text Processing
Classifier: Topic :: Text Processing :: Indexing
Classifier: Topic :: Text Processing :: Linguistic
License-File: LICENSE
Requires-Dist: jpype1 (==1.4.1)
Requires-Dist: hanlp-downloader
